setup.py
hy454.egg-info/PKG-INFO
hy454.egg-info/SOURCES.txt
hy454.egg-info/dependency_links.txt
hy454.egg-info/top_level.txt
lib/hy454/__init__.py
lib/hy454/_annotate.py
lib/hy454/_basefont.py
lib/hy454/_codonaligner.py
lib/hy454/_common.py
lib/hy454/_compensatory.py
lib/hy454/_divestimator.py
lib/hy454/_fel.py
lib/hy454/_graph.py
lib/hy454/_mdr_variants.py
lib/hy454/_preprocessing.py
lib/hy454/_rate_class_neb.py
lib/hy454/_region_extract.py
lib/hy454/_reporter.py
lib/hy454/_resistance.py
lib/hy454/_server.py
lib/hy454/_variants.py
scripts/codonaligner
scripts/coveragegrapher
scripts/seqlogo