Metadata-Version: 1.1
Name: hy454
Version: 0.4.3
Summary: 454 UDS analysis tools
Home-page: http://github.com/veg/hy454
Author: N Lance Hepler
Author-email: nlhepler@gmail.com
License: GNU GPL version 3
Platform: UNKNOWN
Requires: Bio
Requires: BioExt
Requires: fakemp
Requires: freetype
Requires: hppy
Requires: matplotlib
Requires: numpy
